{
    "ADULT_INIT_ITEMS": "03481A50",
    "ADULT_VALID_ITEMS": "03481A58",
    "AUDIO_THREAD_INFO": "03482A3C",
    "AUDIO_THREAD_INFO_MEM_SIZE": "03482A5C",
    "AUDIO_THREAD_INFO_MEM_START": "03482A58",
    "AUDIO_THREAD_MEM_START": "0348C630",
    "BOMBCHUS_IN_LOGIC": "03480C94",
    "CFG_A_BUTTON_COLOR": "03480844",
    "CFG_A_NOTE_COLOR": "03480862",
    "CFG_B_BUTTON_COLOR": "0348084A",
    "CFG_C_BUTTON_COLOR": "03480850",
    "CFG_C_NOTE_COLOR": "03480868",
    "CFG_DAMAGE_MULTIPLYER": "03482730",
    "CFG_DISPLAY_DPAD": "0348086E",
    "CFG_HEART_COLOR": "0348083E",
    "CFG_MAGIC_COLOR": "03480838",
    "CFG_RAINBOW_SWORD_INNER_ENABLED": "0348086F",
    "CFG_RAINBOW_SWORD_OUTER_ENABLED": "03480870",
    "CFG_SHOP_CURSOR_COLOR": "0348085C",
    "CFG_TEXT_CURSOR_COLOR": "03480856",
    "CHEST_SIZE_MATCH_CONTENTS": "0348218C",
    "COOP_CONTEXT": "03480020",
    "COOP_VERSION": "03480020",
    "COSMETIC_CONTEXT": "03480834",
    "COSMETIC_FORMAT_VERSION": "03480834",
    "CURRENT_GROTTO_ID": "034828FE",
    "DEBUG_OFFSET": "03482320",
    "DISABLE_TIMERS": "03480CB0",
    "DPAD_TEXTURE": "0348AE30",
    "DUNGEONS_SHUFFLED": "03480CB2",
    "EXTENDED_OBJECT_TABLE": "03480C74",
    "EXTERN_DAMAGE_MULTIPLYER": "03482731",
    "FAST_CHESTS": "03480CAC",
    "FONT_TEXTURE": "03489968",
    "FREE_SCARECROW_ENABLED": "03480CA4",
    "GET_CHEST_OVERRIDE_COLOR_WRAPPER": "034821BC",
    "GET_CHEST_OVERRIDE_SIZE_WRAPPER": "03482190",
    "GET_ITEM_TRIGGERED": "034813C8",
    "GOSSIP_HINT_CONDITION": "03480CA0",
    "GROTTO_EXIT_LIST": "034828BC",
    "GROTTO_LOAD_TABLE": "03482838",
    "INCOMING_ITEM": "03480028",
    "INCOMING_PLAYER": "03480026",
    "INITIAL_SAVE_DATA": "03480874",
    "JABU_ELEVATOR_ENABLE": "03480CAA",
    "LACS_CONDITION": "03480C9C",
    "MAX_RUPEES": "034888DD",
    "MOVED_ADULT_KING_ZORA": "03482A7C",
    "NO_ESCAPE_SEQUENCE": "034888A8",
    "NO_FOG_STATE": "03480CB1",
    "OCARINAS_SHUFFLED": "03480CAB",
    "OUTGOING_ITEM": "03480030",
    "OUTGOING_KEY": "0348002C",
    "OUTGOING_PLAYER": "03480032",
    "OVERWORLD_SHUFFLED": "03480CB3",
    "PAYLOAD_END": "0348C630",
    "PAYLOAD_START": "03480000",
    "PLAYED_WARP_SONG": "034811CC",
    "PLAYER_ID": "03480024",
    "PLAYER_NAMES": "03480034",
    "PLAYER_NAME_ID": "03480025",
    "RAINBOW_BRIDGE_CONDITION": "03480C98",
    "RAINBOW_BRIDGE_TOKENS": "03480CA8",
    "RANDO_CONTEXT": "03480000",
    "SHUFFLE_BEANS": "03480CAE",
    "SHUFFLE_COWS": "03480CAD",
    "SONGS_AS_ITEMS": "03480CAF",
    "SOS_ITEM_GIVEN": "03481434",
    "SPEED_MULTIPLIER": "034821FC",
    "START_TWINROVA_FIGHT": "03482AFC",
    "TIME_TRAVEL_SAVED_EQUIPS": "03481774",
    "TRIFORCE_ICON_TEXTURE": "0348B630",
    "a_button": "03488870",
    "a_note_b": "0348885C",
    "a_note_font_glow_base": "03488844",
    "a_note_font_glow_max": "03488840",
    "a_note_g": "03488860",
    "a_note_glow_base": "0348884C",
    "a_note_glow_max": "03488848",
    "a_note_r": "03488864",
    "active_item_action_id": "034888C0",
    "active_item_fast_chest": "034888B0",
    "active_item_graphic_id": "034888B4",
    "active_item_object_id": "034888B8",
    "active_item_row": "034888C4",
    "active_item_text_id": "034888BC",
    "active_override": "034888CC",
    "active_override_is_outgoing": "034888C8",
    "b_button": "0348886C",
    "beating_dd": "03488878",
    "beating_no_dd": "03488880",
    "c_button": "03488868",
    "c_note_b": "03488850",
    "c_note_font_glow_base": "03488834",
    "c_note_font_glow_max": "03488830",
    "c_note_g": "03488854",
    "c_note_glow_base": "0348883C",
    "c_note_glow_max": "03488838",
    "c_note_r": "03488858",
    "cfg_dungeon_info_enable": "03488808",
    "cfg_dungeon_info_mq_enable": "034888A0",
    "cfg_dungeon_info_mq_need_map": "0348889C",
    "cfg_dungeon_info_reward_need_altar": "03488894",
    "cfg_dungeon_info_reward_need_compass": "03488898",
    "cfg_dungeon_is_mq": "034888FC",
    "cfg_dungeon_rewards": "0348765C",
    "cfg_file_select_hash": "034888A4",
    "cfg_item_overrides": "03488924",
    "defaultDDHeart": "03488884",
    "defaultHeart": "0348888C",
    "dpad_sprite": "034877A8",
    "dummy_actor": "034888D4",
    "dungeon_count": "0348880C",
    "dungeons": "03487680",
    "extern_ctxt": "0348771C",
    "font_sprite": "034877B8",
    "freecam_modes": "034875A0",
    "hash_sprites": "03488818",
    "hash_symbols": "03487730",
    "heap_next": "034888F8",
    "item_overrides_count": "034888D8",
    "item_table": "03487814",
    "items_sprite": "034877D8",
    "last_fog_distance": "03488810",
    "medal_colors": "0348766C",
    "medals_sprite": "034877E8",
    "normal_dd": "03488874",
    "normal_no_dd": "0348887C",
    "object_slots": "03489924",
    "pending_freezes": "034888DC",
    "pending_item_queue": "0348890C",
    "quest_items_sprite": "034877C8",
    "rupee_colors": "03487808",
    "satisified_pending_frames": "034888AC",
    "scene_fog_distance": "03488814",
    "setup_db": "03487770",
    "stones_sprite": "034877F8",
    "text_cursor_border_base": "03488824",
    "text_cursor_border_max": "03488820",
    "text_cursor_inner_base": "0348882C",
    "text_cursor_inner_max": "03488828",
    "triforce_hunt_enabled": "034888EC",
    "triforce_pieces_requied": "03488892",
    "triforce_sprite": "03487798"
}