{
    "ADULT_INIT_ITEMS": "03481B08",
    "ADULT_VALID_ITEMS": "03481B10",
    "AUDIO_THREAD_INFO": "03482AF4",
    "AUDIO_THREAD_INFO_MEM_SIZE": "03482B14",
    "AUDIO_THREAD_INFO_MEM_START": "03482B10",
    "AUDIO_THREAD_MEM_START": "0348CAB0",
    "BOMBCHUS_IN_LOGIC": "03480C94",
    "CFG_A_BUTTON_COLOR": "03480844",
    "CFG_A_NOTE_COLOR": "03480862",
    "CFG_B_BUTTON_COLOR": "0348084A",
    "CFG_C_BUTTON_COLOR": "03480850",
    "CFG_C_NOTE_COLOR": "03480868",
    "CFG_DAMAGE_MULTIPLYER": "034827E8",
    "CFG_DISPLAY_DPAD": "0348086E",
    "CFG_HEART_COLOR": "0348083E",
    "CFG_MAGIC_COLOR": "03480838",
    "CFG_RAINBOW_SWORD_INNER_ENABLED": "0348086F",
    "CFG_RAINBOW_SWORD_OUTER_ENABLED": "03480870",
    "CFG_SHOP_CURSOR_COLOR": "0348085C",
    "CFG_TEXT_CURSOR_COLOR": "03480856",
    "CHEST_SIZE_MATCH_CONTENTS": "03482244",
    "COOP_CONTEXT": "03480020",
    "COOP_VERSION": "03480020",
    "COSMETIC_CONTEXT": "03480834",
    "COSMETIC_FORMAT_VERSION": "03480834",
    "CURRENT_GROTTO_ID": "034829B6",
    "DEBUG_OFFSET": "034823D8",
    "DISABLE_TIMERS": "03480CB0",
    "DPAD_TEXTURE": "0348B2B0",
    "DUNGEONS_SHUFFLED": "03480CB2",
    "EXTENDED_OBJECT_TABLE": "03480C74",
    "EXTERN_DAMAGE_MULTIPLYER": "034827E9",
    "FAST_CHESTS": "03480CAC",
    "FONT_TEXTURE": "03489DE8",
    "FREE_SCARECROW_ENABLED": "03480CA4",
    "GET_CHEST_OVERRIDE_COLOR_WRAPPER": "03482274",
    "GET_CHEST_OVERRIDE_SIZE_WRAPPER": "03482248",
    "GET_ITEM_TRIGGERED": "034813C8",
    "GOSSIP_HINT_CONDITION": "03480CA0",
    "GROTTO_EXIT_LIST": "03482974",
    "GROTTO_LOAD_TABLE": "034828F0",
    "INCOMING_ITEM": "03480028",
    "INCOMING_PLAYER": "03480026",
    "INITIAL_SAVE_DATA": "03480874",
    "JABU_ELEVATOR_ENABLE": "03480CAA",
    "LACS_CONDITION": "03480C9C",
    "MAX_RUPEES": "03488D5D",
    "MINIGAME_SWORDLESS": "03482E78",
    "MOVED_ADULT_KING_ZORA": "03482B34",
    "NO_ESCAPE_SEQUENCE": "03488D28",
    "NO_FOG_STATE": "03480CB1",
    "OCARINAS_SHUFFLED": "03480CAB",
    "OUTGOING_ITEM": "03480030",
    "OUTGOING_KEY": "0348002C",
    "OUTGOING_PLAYER": "03480032",
    "OVERWORLD_SHUFFLED": "03480CB3",
    "PAYLOAD_END": "0348CAB0",
    "PAYLOAD_START": "03480000",
    "PLAYED_WARP_SONG": "034811CC",
    "PLAYER_ID": "03480024",
    "PLAYER_NAMES": "03480034",
    "PLAYER_NAME_ID": "03480025",
    "RAINBOW_BRIDGE_CONDITION": "03480C98",
    "RAINBOW_BRIDGE_TOKENS": "03480CA8",
    "RANDO_CONTEXT": "03480000",
    "SHUFFLE_BEANS": "03480CAE",
    "SHUFFLE_COWS": "03480CAD",
    "SONGS_AS_ITEMS": "03480CAF",
    "SOS_ITEM_GIVEN": "03481434",
    "SPEED_MULTIPLIER": "034822B4",
    "START_TWINROVA_FIGHT": "03482BB4",
    "TIME_TRAVEL_SAVED_EQUIPS": "0348182C",
    "TRIFORCE_ICON_TEXTURE": "0348BAB0",
    "a_button": "03488CF0",
    "a_note_b": "03488CDC",
    "a_note_font_glow_base": "03488CC4",
    "a_note_font_glow_max": "03488CC0",
    "a_note_g": "03488CE0",
    "a_note_glow_base": "03488CCC",
    "a_note_glow_max": "03488CC8",
    "a_note_r": "03488CE4",
    "active_item_action_id": "03488D40",
    "active_item_fast_chest": "03488D30",
    "active_item_graphic_id": "03488D34",
    "active_item_object_id": "03488D38",
    "active_item_row": "03488D44",
    "active_item_text_id": "03488D3C",
    "active_override": "03488D4C",
    "active_override_is_outgoing": "03488D48",
    "b_button": "03488CEC",
    "beating_dd": "03488CF8",
    "beating_no_dd": "03488D00",
    "c_button": "03488CE8",
    "c_note_b": "03488CD0",
    "c_note_font_glow_base": "03488CB4",
    "c_note_font_glow_max": "03488CB0",
    "c_note_g": "03488CD4",
    "c_note_glow_base": "03488CBC",
    "c_note_glow_max": "03488CB8",
    "c_note_r": "03488CD8",
    "cfg_dungeon_info_enable": "03488C88",
    "cfg_dungeon_info_mq_enable": "03488D20",
    "cfg_dungeon_info_mq_need_map": "03488D1C",
    "cfg_dungeon_info_reward_need_altar": "03488D14",
    "cfg_dungeon_info_reward_need_compass": "03488D18",
    "cfg_dungeon_is_mq": "03488D7C",
    "cfg_dungeon_rewards": "03487ADC",
    "cfg_file_select_hash": "03488D24",
    "cfg_item_overrides": "03488DA4",
    "defaultDDHeart": "03488D04",
    "defaultHeart": "03488D0C",
    "dpad_sprite": "03487C28",
    "dummy_actor": "03488D54",
    "dungeon_count": "03488C8C",
    "dungeons": "03487B00",
    "extern_ctxt": "03487B9C",
    "font_sprite": "03487C38",
    "freecam_modes": "03487A20",
    "hash_sprites": "03488C98",
    "hash_symbols": "03487BB0",
    "heap_next": "03488D78",
    "item_overrides_count": "03488D58",
    "item_table": "03487C94",
    "items_sprite": "03487C58",
    "last_fog_distance": "03488C90",
    "medal_colors": "03487AEC",
    "medals_sprite": "03487C68",
    "normal_dd": "03488CF4",
    "normal_no_dd": "03488CFC",
    "object_slots": "03489DA4",
    "pending_freezes": "03488D5C",
    "pending_item_queue": "03488D8C",
    "quest_items_sprite": "03487C48",
    "rupee_colors": "03487C88",
    "satisified_pending_frames": "03488D2C",
    "scene_fog_distance": "03488C94",
    "setup_db": "03487BF0",
    "stones_sprite": "03487C78",
    "text_cursor_border_base": "03488CA4",
    "text_cursor_border_max": "03488CA0",
    "text_cursor_inner_base": "03488CAC",
    "text_cursor_inner_max": "03488CA8",
    "triforce_hunt_enabled": "03488D6C",
    "triforce_pieces_requied": "03488D12",
    "triforce_sprite": "03487C18"
}