{
    "ADULT_INIT_ITEMS": "03481B08",
    "ADULT_VALID_ITEMS": "03481B10",
    "AUDIO_THREAD_INFO": "03482AF4",
    "AUDIO_THREAD_INFO_MEM_SIZE": "03482B14",
    "AUDIO_THREAD_INFO_MEM_START": "03482B10",
    "AUDIO_THREAD_MEM_START": "0348C930",
    "BOMBCHUS_IN_LOGIC": "03480C94",
    "CFG_A_BUTTON_COLOR": "03480844",
    "CFG_A_NOTE_COLOR": "03480862",
    "CFG_B_BUTTON_COLOR": "0348084A",
    "CFG_C_BUTTON_COLOR": "03480850",
    "CFG_C_NOTE_COLOR": "03480868",
    "CFG_DAMAGE_MULTIPLYER": "034827E8",
    "CFG_DISPLAY_DPAD": "0348086E",
    "CFG_HEART_COLOR": "0348083E",
    "CFG_MAGIC_COLOR": "03480838",
    "CFG_RAINBOW_SWORD_INNER_ENABLED": "0348086F",
    "CFG_RAINBOW_SWORD_OUTER_ENABLED": "03480870",
    "CFG_SHOP_CURSOR_COLOR": "0348085C",
    "CFG_TEXT_CURSOR_COLOR": "03480856",
    "CHEST_SIZE_MATCH_CONTENTS": "03482244",
    "COOP_CONTEXT": "03480020",
    "COOP_VERSION": "03480020",
    "COSMETIC_CONTEXT": "03480834",
    "COSMETIC_FORMAT_VERSION": "03480834",
    "CURRENT_GROTTO_ID": "034829B6",
    "DEBUG_OFFSET": "034823D8",
    "DISABLE_TIMERS": "03480CB0",
    "DPAD_TEXTURE": "0348B130",
    "DUNGEONS_SHUFFLED": "03480CB2",
    "EXTENDED_OBJECT_TABLE": "03480C74",
    "EXTERN_DAMAGE_MULTIPLYER": "034827E9",
    "FAST_CHESTS": "03480CAC",
    "FONT_TEXTURE": "03489C68",
    "FREE_SCARECROW_ENABLED": "03480CA4",
    "GET_CHEST_OVERRIDE_COLOR_WRAPPER": "03482274",
    "GET_CHEST_OVERRIDE_SIZE_WRAPPER": "03482248",
    "GET_ITEM_TRIGGERED": "034813C8",
    "GOSSIP_HINT_CONDITION": "03480CA0",
    "GROTTO_EXIT_LIST": "03482974",
    "GROTTO_LOAD_TABLE": "034828F0",
    "INCOMING_ITEM": "03480028",
    "INCOMING_PLAYER": "03480026",
    "INITIAL_SAVE_DATA": "03480874",
    "JABU_ELEVATOR_ENABLE": "03480CAA",
    "LACS_CONDITION": "03480C9C",
    "MAX_RUPEES": "03488BDD",
    "MOVED_ADULT_KING_ZORA": "03482B34",
    "NO_ESCAPE_SEQUENCE": "03488BA8",
    "NO_FOG_STATE": "03480CB1",
    "OCARINAS_SHUFFLED": "03480CAB",
    "OUTGOING_ITEM": "03480030",
    "OUTGOING_KEY": "0348002C",
    "OUTGOING_PLAYER": "03480032",
    "OVERWORLD_SHUFFLED": "03480CB3",
    "PAYLOAD_END": "0348C930",
    "PAYLOAD_START": "03480000",
    "PLAYED_WARP_SONG": "034811CC",
    "PLAYER_ID": "03480024",
    "PLAYER_NAMES": "03480034",
    "PLAYER_NAME_ID": "03480025",
    "RAINBOW_BRIDGE_CONDITION": "03480C98",
    "RAINBOW_BRIDGE_TOKENS": "03480CA8",
    "RANDO_CONTEXT": "03480000",
    "SHUFFLE_BEANS": "03480CAE",
    "SHUFFLE_COWS": "03480CAD",
    "SONGS_AS_ITEMS": "03480CAF",
    "SOS_ITEM_GIVEN": "03481434",
    "SPEED_MULTIPLIER": "034822B4",
    "START_TWINROVA_FIGHT": "03482BB4",
    "TIME_TRAVEL_SAVED_EQUIPS": "0348182C",
    "TRIFORCE_ICON_TEXTURE": "0348B930",
    "a_button": "03488B70",
    "a_note_b": "03488B5C",
    "a_note_font_glow_base": "03488B44",
    "a_note_font_glow_max": "03488B40",
    "a_note_g": "03488B60",
    "a_note_glow_base": "03488B4C",
    "a_note_glow_max": "03488B48",
    "a_note_r": "03488B64",
    "active_item_action_id": "03488BC0",
    "active_item_fast_chest": "03488BB0",
    "active_item_graphic_id": "03488BB4",
    "active_item_object_id": "03488BB8",
    "active_item_row": "03488BC4",
    "active_item_text_id": "03488BBC",
    "active_override": "03488BCC",
    "active_override_is_outgoing": "03488BC8",
    "b_button": "03488B6C",
    "beating_dd": "03488B78",
    "beating_no_dd": "03488B80",
    "c_button": "03488B68",
    "c_note_b": "03488B50",
    "c_note_font_glow_base": "03488B34",
    "c_note_font_glow_max": "03488B30",
    "c_note_g": "03488B54",
    "c_note_glow_base": "03488B3C",
    "c_note_glow_max": "03488B38",
    "c_note_r": "03488B58",
    "cfg_dungeon_info_enable": "03488B08",
    "cfg_dungeon_info_mq_enable": "03488BA0",
    "cfg_dungeon_info_mq_need_map": "03488B9C",
    "cfg_dungeon_info_reward_need_altar": "03488B94",
    "cfg_dungeon_info_reward_need_compass": "03488B98",
    "cfg_dungeon_is_mq": "03488BFC",
    "cfg_dungeon_rewards": "0348795C",
    "cfg_file_select_hash": "03488BA4",
    "cfg_item_overrides": "03488C24",
    "defaultDDHeart": "03488B84",
    "defaultHeart": "03488B8C",
    "dpad_sprite": "03487AA8",
    "dummy_actor": "03488BD4",
    "dungeon_count": "03488B0C",
    "dungeons": "03487980",
    "extern_ctxt": "03487A1C",
    "font_sprite": "03487AB8",
    "freecam_modes": "034878A0",
    "hash_sprites": "03488B18",
    "hash_symbols": "03487A30",
    "heap_next": "03488BF8",
    "item_overrides_count": "03488BD8",
    "item_table": "03487B14",
    "items_sprite": "03487AD8",
    "last_fog_distance": "03488B10",
    "medal_colors": "0348796C",
    "medals_sprite": "03487AE8",
    "normal_dd": "03488B74",
    "normal_no_dd": "03488B7C",
    "object_slots": "03489C24",
    "pending_freezes": "03488BDC",
    "pending_item_queue": "03488C0C",
    "quest_items_sprite": "03487AC8",
    "rupee_colors": "03487B08",
    "satisified_pending_frames": "03488BAC",
    "scene_fog_distance": "03488B14",
    "setup_db": "03487A70",
    "stones_sprite": "03487AF8",
    "text_cursor_border_base": "03488B24",
    "text_cursor_border_max": "03488B20",
    "text_cursor_inner_base": "03488B2C",
    "text_cursor_inner_max": "03488B28",
    "triforce_hunt_enabled": "03488BEC",
    "triforce_pieces_requied": "03488B92",
    "triforce_sprite": "03487A98"
}