{
    "ADULT_INIT_ITEMS": "03481EE0",
    "ADULT_VALID_ITEMS": "03481EE8",
    "BOMBCHUS_IN_LOGIC": "03481408",
    "CFG_DISPLAY_DPAD": "03481004",
    "CFG_RAINBOW_SWORD_INNER_ENABLED": "03481005",
    "CFG_RAINBOW_SWORD_OUTER_ENABLED": "03481006",
    "CHEST_SIZE_MATCH_CONTENTS": "03482548",
    "COOP_VERSION": "03480000",
    "COSMETIC_FORMAT_VERSION": "03481000",
    "DEBUG_OFFSET": "03482608",
    "DPAD_TEXTURE": "034895A0",
    "FAST_CHESTS": "0348141A",
    "FONT_TEXTURE": "034880D8",
    "FREE_SCARECROW_ENABLED": "03481414",
    "GET_CHEST_OVERRIDE_COLOR_WRAPPER": "03482578",
    "GET_CHEST_OVERRIDE_SIZE_WRAPPER": "0348254C",
    "GOSSIP_HINT_CONDITION": "03481410",
    "INCOMING_ITEM": "03480006",
    "INITIAL_SAVE_DATA": "03481008",
    "JABU_ELEVATOR_ENABLE": "03481418",
    "NO_ESCAPE_SEQUENCE": "03487024",
    "OCARINAS_SHUFFLED": "03481419",
    "OUTGOING_ITEM": "0348000C",
    "OUTGOING_KEY": "03480008",
    "OUTGOING_PLAYER": "0348000E",
    "PLAYER_ID": "03480004",
    "PLAYER_NAMES": "03480010",
    "PLAYER_NAME_ID": "03480005",
    "RAINBOW_BRIDGE_CONDITION": "0348140C",
    "SHUFFLE_COWS": "0348141B",
    "TIME_TRAVEL_SAVED_EQUIPS": "03481C04",
    "active_item_action_id": "0348703C",
    "active_item_fast_chest": "0348702C",
    "active_item_graphic_id": "03487030",
    "active_item_object_id": "03487034",
    "active_item_row": "03487040",
    "active_item_text_id": "03487038",
    "active_override": "03487048",
    "active_override_is_outgoing": "03487044",
    "cfg_dungeon_info_enable": "03487000",
    "cfg_dungeon_info_mq_enable": "0348701C",
    "cfg_dungeon_info_mq_need_map": "03487018",
    "cfg_dungeon_info_reward_need_altar": "03487010",
    "cfg_dungeon_info_reward_need_compass": "03487014",
    "cfg_dungeon_is_mq": "0348706C",
    "cfg_dungeon_rewards": "03485EC0",
    "cfg_file_select_hash": "03487020",
    "cfg_item_overrides": "03487094",
    "dpad_sprite": "03485FE8",
    "dummy_actor": "03487050",
    "dungeon_count": "03487004",
    "dungeons": "03485EE4",
    "font_sprite": "03485FF8",
    "hash_sprites": "03487008",
    "hash_symbols": "03485F80",
    "heap_next": "03487068",
    "item_overrides_count": "03487054",
    "item_table": "03486048",
    "items_sprite": "03486018",
    "medal_colors": "03485ED0",
    "medals_sprite": "03486028",
    "object_slots": "03488094",
    "pending_freezes": "03487058",
    "pending_item_queue": "0348707C",
    "quest_items_sprite": "03486008",
    "satisified_pending_frames": "03487028",
    "setup_db": "03485FC0",
    "stones_sprite": "03486038"
}